.gitignore
LICENSE
readme.md
setup.cfg
setup.py
cli/__init__.py
cli/railgun.py
cli/operators/__init__.py
cli/operators/_copy_files.py
cli/operators/_mkdir_p.py
cli/operators/_touch_file.py
cli/templates/__init__.py
cli/templates/md.py
gen/__init__.py
railgun_cli.egg-info/PKG-INFO
railgun_cli.egg-info/SOURCES.txt
railgun_cli.egg-info/dependency_links.txt
railgun_cli.egg-info/entry_points.txt
railgun_cli.egg-info/not-zip-safe
railgun_cli.egg-info/requires.txt
railgun_cli.egg-info/top_level.txt
site/.site
site/config.py
site/manage.py
site/requirement.txt
site/app/__init__.py
site/app/paginate.py
site/app/views.py
site/app/pages/hello.md
site/app/templates/index.html
site/app/themes/readme.md