Metadata-Version: 1.1
Name: railgun-cli
Version: 0.1.2
Summary: py static site generator, simple and fast
Home-page: https://github.com/neo1218/railgun
Author: neo1218
Author-email: neo1218@yeah.net
License: MIT
Platform: any
Classifier: Environment :: Web Environment
Classifier: Intended Audience :: Developers
Classifier: License :: OSI Approved :: MIT License
Classifier: Operating System :: OS Independent
Classifier: Programming Language :: Python
Classifier: Topic :: Internet :: WWW/HTTP :: Dynamic Content
Classifier: Topic :: Software Development :: Libraries :: Python Modules
